ASRChild/__init__.py
ASRChild/Dataset/__init__.py
ASRChild/Dataset/AudioConversion/AudioConvert.py
ASRChild/Dataset/AudioConversion/AudioData.py
ASRChild/Dataset/AudioConversion/__init__.py
ASRChild/Dataset/AudioConversion/test.py
ASRChild/Dataset/DataPipeline/CoreDataset.py
ASRChild/Dataset/DataPipeline/DataFactory.py
ASRChild/Dataset/DataPipeline/__init__.py
ASRChild/Model/__init__.py
ASRChild/Model/ASRModel/CTCDecoder.py
ASRChild/Model/ASRModel/ContextualASR.py
ASRChild/Model/ASRModel/DecoderModel.py
ASRChild/Model/ASRModel/ExternalAM.py
ASRChild/Model/ASRModel/ExternalLM.py
ASRChild/Model/ASRModel/__init__.py
ASRChild/Training/Training.py
ASRChild/Training/TrainingWrap.py
ASRChild/Training/__init__.py
ASRChild/Utils/ConfigGenerator.py
ASRChild/Utils/__init__.py
ASRChild-0.0.1.dist-info/LICENSE
ASRChild-0.0.1.dist-info/METADATA
ASRChild-0.0.1.dist-info/WHEEL
ASRChild-0.0.1.dist-info/top_level.txt
ASRChild-0.0.1.dist-info/RECORD
