Metadata-Version: 2.1
Name: ASRChild
Version: 0.0.1
Summary: Package for ASRChild
Author-email: Yihao Wang <i@yihaow.me>, Zhongdi Wu <ultronwu@gmail.com>
License: MIT License
Requires-Python: >=3.10
License-File: LICENSE
Requires-Dist: torch
Requires-Dist: torchtune
Requires-Dist: rich
Requires-Dist: lightning
Requires-Dist: torchmetrics
Requires-Dist: icecream
Requires-Dist: safetensors
Requires-Dist: wandb
Requires-Dist: torchao
Requires-Dist: transformers
Requires-Dist: deepspeed
